[{"id":52,"name":"Ashkāsham","state_id":3901,"state_code":"BDS"},{"id":68,"name":"Fayzabad","state_id":3901,"state_code":"BDS"},{"id":78,"name":"Jurm","state_id":3901,"state_code":"BDS"},{"id":84,"name":"Khandūd","state_id":3901,"state_code":"BDS"},{"id":115,"name":"Rāghistān","state_id":3901,"state_code":"BDS"},{"id":131,"name":"Wākhān","state_id":3901,"state_code":"BDS"},{"id":72,"name":"Ghormach","state_id":3871,"state_code":"BDG"},{"id":108,"name":"Qala i Naw","state_id":3871,"state_code":"BDG"},{"id":54,"name":"Baghlān","state_id":3875,"state_code":"BGL"},{"id":140,"name":"Ḩukūmatī Dahanah-ye Ghōrī","state_id":3875,"state_code":"BGL"},{"id":101,"name":"Nahrīn","state_id":3875,"state_code":"BGL"},{"id":105,"name":"Pul-e Khumrī","state_id":3875,"state_code":"BGL"},{"id":55,"name":"Balkh","state_id":3884,"state_code":"BAL"},{"id":65,"name":"Dowlatābād","state_id":3884,"state_code":"BAL"},{"id":85,"name":"Khulm","state_id":3884,"state_code":"BAL"},{"id":91,"name":"Lab-Sar","state_id":3884,"state_code":"BAL"},{"id":97,"name":"Mazār-e Sharīf","state_id":3884,"state_code":"BAL"},{"id":112,"name":"Qarchī Gak","state_id":3884,"state_code":"BAL"},{"id":57,"name":"Bāmyān","state_id":3872,"state_code":"BAM"},{"id":104,"name":"Panjāb","state_id":3872,"state_code":"BAM"},{"id":102,"name":"Nīlī","state_id":3892,"state_code":"DAY"},{"id":66,"name":"Farah","state_id":3899,"state_code":"FRA"},{"id":50,"name":"Andkhoy","state_id":3889,"state_code":"FYB"},{"id":96,"name":"Maymana","state_id":3889,"state_code":"FYB"},{"id":71,"name":"Ghazni","state_id":3870,"state_code":"GHA"},{"id":67,"name":"Fayrōz Kōh","state_id":3888,"state_code":"GHO"},{"id":121,"name":"Shahrak","state_id":3888,"state_code":"GHO"},{"id":141,"name":"‘Alāqahdārī Dīshū","state_id":3873,"state_code":"HEL"},{"id":70,"name":"Gereshk","state_id":3873,"state_code":"HEL"},{"id":93,"name":"Lashkar Gāh","state_id":3873,"state_code":"HEL"},{"id":95,"name":"Markaz-e Ḩukūmat-e Darwēshān","state_id":3873,"state_code":"HEL"},{"id":118,"name":"Sangīn","state_id":3873,"state_code":"HEL"},{"id":60,"name":"Chahār Burj","state_id":3887,"state_code":"HER"},{"id":73,"name":"Ghōriyān","state_id":3887,"state_code":"HER"},{"id":74,"name":"Herāt","state_id":3887,"state_code":"HER"},{"id":80,"name":"Kafir Qala","state_id":3887,"state_code":"HER"},{"id":82,"name":"Karukh","state_id":3887,"state_code":"HER"},{"id":88,"name":"Kuhsān","state_id":3887,"state_code":"HER"},{"id":90,"name":"Kushk","state_id":3887,"state_code":"HER"},{"id":111,"name":"Qarah Bāgh","state_id":3887,"state_code":"HER"},{"id":123,"name":"Shīnḏanḏ","state_id":3887,"state_code":"HER"},{"id":129,"name":"Tīr Pul","state_id":3887,"state_code":"HER"},{"id":135,"name":"Zindah Jān","state_id":3887,"state_code":"HER"},{"id":136,"name":"Āqchah","state_id":3886,"state_code":"JOW"},{"id":63,"name":"Darzāb","state_id":3886,"state_code":"JOW"},{"id":113,"name":"Qarqīn","state_id":3886,"state_code":"JOW"},{"id":122,"name":"Shibirghān","state_id":3886,"state_code":"JOW"},{"id":79,"name":"Kabul","state_id":3902,"state_code":"KAB"},{"id":99,"name":"Mīr Bachah Kōṯ","state_id":3902,"state_code":"KAB"},{"id":103,"name":"Paghmān","state_id":3902,"state_code":"KAB"},{"id":81,"name":"Kandahār","state_id":3890,"state_code":"KAN"},{"id":124,"name":"Sidqābād","state_id":3879,"state_code":"KAP"},{"id":87,"name":"Khōst","state_id":3878,"state_code":"KHO"},{"id":51,"name":"Asadabad","state_id":3876,"state_code":"KNR"},{"id":138,"name":"Āsmār","state_id":3876,"state_code":"KNR"},{"id":64,"name":"Dasht-e Archī","state_id":3900,"state_code":"KDZ"},{"id":75,"name":"Imām Şāḩib","state_id":3900,"state_code":"KDZ"},{"id":83,"name":"Khanabad","state_id":3900,"state_code":"KDZ"},{"id":89,"name":"Kunduz","state_id":3900,"state_code":"KDZ"},{"id":114,"name":"Qarāwul","state_id":3900,"state_code":"KDZ"},{"id":98,"name":"Mehtar Lām","state_id":3891,"state_code":"LAG"},{"id":56,"name":"Baraki Barak","state_id":3897,"state_code":"LOG"},{"id":139,"name":"Ḩukūmatī Azrah","state_id":3897,"state_code":"LOG"},{"id":106,"name":"Pul-e ‘Alam","state_id":3897,"state_code":"LOG"},{"id":58,"name":"Bāsawul","state_id":3882,"state_code":"NAN"},{"id":77,"name":"Jalālābād","state_id":3882,"state_code":"NAN"},{"id":86,"name":"Khāsh","state_id":3896,"state_code":"NIM"},{"id":100,"name":"Mīrābād","state_id":3896,"state_code":"NIM"},{"id":116,"name":"Rūdbār","state_id":3896,"state_code":"NIM"},{"id":132,"name":"Zaranj","state_id":3896,"state_code":"NIM"},{"id":107,"name":"Pārūn","state_id":3880,"state_code":"NUR"},{"id":69,"name":"Gardez","state_id":3894,"state_code":"PIA"},{"id":120,"name":"Saṟōbī","state_id":3877,"state_code":"PKA"},{"id":134,"name":"Zaṟah Sharan","state_id":3877,"state_code":"PKA"},{"id":133,"name":"Zarghūn Shahr","state_id":3877,"state_code":"PKA"},{"id":59,"name":"Bāzārak","state_id":3881,"state_code":"PAN"},{"id":61,"name":"Charikar","state_id":3895,"state_code":"PAR"},{"id":76,"name":"Jabal os Saraj","state_id":3895,"state_code":"PAR"},{"id":53,"name":"Aībak","state_id":3883,"state_code":"SAM"},{"id":62,"name":"Chīras","state_id":3885,"state_code":"SAR"},{"id":92,"name":"Larkird","state_id":3885,"state_code":"SAR"},{"id":110,"name":"Qal‘ah-ye Shahr","state_id":3885,"state_code":"SAR"},{"id":117,"name":"Sang-e Chārak","state_id":3885,"state_code":"SAR"},{"id":119,"name":"Sar-e Pul","state_id":3885,"state_code":"SAR"},{"id":125,"name":"Tagāw-Bāy","state_id":3885,"state_code":"SAR"},{"id":128,"name":"Tukzār","state_id":3885,"state_code":"SAR"},{"id":137,"name":"Ārt Khwājah","state_id":3893,"state_code":"TAK"},{"id":126,"name":"Taloqan","state_id":3893,"state_code":"TAK"},{"id":127,"name":"Tarinkot","state_id":3898,"state_code":"URU"},{"id":130,"name":"Uruzgān","state_id":3898,"state_code":"URU"},{"id":157060,"name":"Chaki Wardak","state_id":5468,"state_code":"WAR"},{"id":157064,"name":"Day Mirdad","state_id":5468,"state_code":"WAR"},{"id":157065,"name":"Hisa-i-Awali Bihsud","state_id":5468,"state_code":"WAR"},{"id":157067,"name":"Jaghatu","state_id":5468,"state_code":"WAR"},{"id":157061,"name":"Jalrez","state_id":5468,"state_code":"WAR"},{"id":157059,"name":"Maidan Shahr","state_id":5468,"state_code":"WAR"},{"id":157066,"name":"Markaz-i-Bihsud","state_id":5468,"state_code":"WAR"},{"id":157062,"name":"Nerkh","state_id":5468,"state_code":"WAR"},{"id":157063,"name":"Sayed Abad","state_id":5468,"state_code":"WAR"},{"id":109,"name":"Qalāt","state_id":3874,"state_code":"ZAB"}]