[{"id":65572,"name":"Al Aḩmadī","state_id":977,"state_code":"AH"},{"id":65574,"name":"Al Faḩāḩīl","state_id":977,"state_code":"AH"},{"id":65575,"name":"Al Finţās","state_id":977,"state_code":"AH"},{"id":65578,"name":"Al Mahbūlah","state_id":977,"state_code":"AH"},{"id":65579,"name":"Al Manqaf","state_id":977,"state_code":"AH"},{"id":65580,"name":"Al Wafrah","state_id":977,"state_code":"AH"},{"id":65582,"name":"Ar Riqqah","state_id":977,"state_code":"AH"},{"id":65571,"name":"Ad Dasmah","state_id":976,"state_code":"KU"},{"id":65584,"name":"Ar Rābiyah","state_id":976,"state_code":"KU"},{"id":65586,"name":"Ash Shāmīyah","state_id":976,"state_code":"KU"},{"id":65587,"name":"Az Zawr","state_id":976,"state_code":"KU"},{"id":65590,"name":"Kuwait City","state_id":976,"state_code":"KU"},{"id":65573,"name":"Al Farwānīyah","state_id":975,"state_code":"FA"},{"id":65589,"name":"Janūb as Surrah","state_id":975,"state_code":"FA"},{"id":65577,"name":"Al Jahrā’","state_id":972,"state_code":"JA"},{"id":65583,"name":"Ar Rumaythīyah","state_id":973,"state_code":"HA"},{"id":65585,"name":"As Sālimīyah","state_id":973,"state_code":"HA"},{"id":65588,"name":"Bayān","state_id":973,"state_code":"HA"},{"id":65593,"name":"Ḩawallī","state_id":973,"state_code":"HA"},{"id":65591,"name":"Salwá","state_id":973,"state_code":"HA"},{"id":65569,"name":"Abu Al Hasaniya","state_id":974,"state_code":"MU"},{"id":65570,"name":"Abu Fatira","state_id":974,"state_code":"MU"},{"id":65576,"name":"Al Funayţīs","state_id":974,"state_code":"MU"},{"id":65581,"name":"Al-Masayel","state_id":974,"state_code":"MU"},{"id":65592,"name":"Şabāḩ as Sālim","state_id":974,"state_code":"MU"}]