[{"id":104606,"name":"Barma","state_id":914,"state_code":"E"},{"id":104609,"name":"Blama","state_id":914,"state_code":"E"},{"id":104612,"name":"Boajibu","state_id":914,"state_code":"E"},{"id":104617,"name":"Buedu","state_id":914,"state_code":"E"},{"id":104620,"name":"Bunumbu","state_id":914,"state_code":"E"},{"id":104621,"name":"Daru","state_id":914,"state_code":"E"},{"id":104627,"name":"Giehun","state_id":914,"state_code":"E"},{"id":104628,"name":"Gorahun","state_id":914,"state_code":"E"},{"id":104629,"name":"Hangha","state_id":914,"state_code":"E"},{"id":104631,"name":"Jojoima","state_id":914,"state_code":"E"},{"id":104633,"name":"Kailahun","state_id":914,"state_code":"E"},{"id":104634,"name":"Kailahun District","state_id":914,"state_code":"E"},{"id":104638,"name":"Kayima","state_id":914,"state_code":"E"},{"id":104639,"name":"Kenema","state_id":914,"state_code":"E"},{"id":104640,"name":"Kenema District","state_id":914,"state_code":"E"},{"id":104642,"name":"Koidu","state_id":914,"state_code":"E"},{"id":104645,"name":"Kono","state_id":914,"state_code":"E"},{"id":104647,"name":"Koyima","state_id":914,"state_code":"E"},{"id":104658,"name":"Manowa","state_id":914,"state_code":"E"},{"id":104662,"name":"Mobai","state_id":914,"state_code":"E"},{"id":104664,"name":"Motema","state_id":914,"state_code":"E"},{"id":104668,"name":"Panguma","state_id":914,"state_code":"E"},{"id":104669,"name":"Pendembu","state_id":914,"state_code":"E"},{"id":104677,"name":"Segbwema","state_id":914,"state_code":"E"},{"id":104680,"name":"Simbakoro","state_id":914,"state_code":"E"},{"id":104682,"name":"Tefeya","state_id":914,"state_code":"E"},{"id":104684,"name":"Tombodu","state_id":914,"state_code":"E"},{"id":104685,"name":"Tombu","state_id":914,"state_code":"E"},{"id":104689,"name":"Wima","state_id":914,"state_code":"E"},{"id":104690,"name":"Yengema","state_id":914,"state_code":"E"},{"id":104635,"name":"Kamakwie","state_id":5697,"state_code":"NW"},{"id":104636,"name":"Kambia","state_id":5697,"state_code":"NW"},{"id":104651,"name":"Lunsar","state_id":5697,"state_code":"NW"},{"id":104670,"name":"Pepel","state_id":5697,"state_code":"NW"},{"id":160111,"name":"Port Loko","state_id":5697,"state_code":"NW"},{"id":104674,"name":"Rokupr","state_id":5697,"state_code":"NW"},{"id":104603,"name":"Alikalia","state_id":911,"state_code":"N"},{"id":104607,"name":"Bindi","state_id":911,"state_code":"N"},{"id":104608,"name":"Binkolo","state_id":911,"state_code":"N"},{"id":104613,"name":"Bombali","state_id":911,"state_code":"N"},{"id":104618,"name":"Bumbuna","state_id":911,"state_code":"N"},{"id":104625,"name":"Gberia Fotombu","state_id":911,"state_code":"N"},{"id":104632,"name":"Kabala","state_id":911,"state_code":"N"},{"id":104637,"name":"Kassiri","state_id":911,"state_code":"N"},{"id":104643,"name":"Koinadugu","state_id":911,"state_code":"N"},{"id":104644,"name":"Konakridee","state_id":911,"state_code":"N"},{"id":104648,"name":"Kukuna","state_id":911,"state_code":"N"},{"id":104650,"name":"Loma","state_id":911,"state_code":"N"},{"id":104652,"name":"Magburaka","state_id":911,"state_code":"N"},{"id":104653,"name":"Makali","state_id":911,"state_code":"N"},{"id":104654,"name":"Makeni","state_id":911,"state_code":"N"},{"id":104655,"name":"Mambolo","state_id":911,"state_code":"N"},{"id":104657,"name":"Mange","state_id":911,"state_code":"N"},{"id":104659,"name":"Masaka","state_id":911,"state_code":"N"},{"id":104660,"name":"Masingbi","state_id":911,"state_code":"N"},{"id":104661,"name":"Masoyila","state_id":911,"state_code":"N"},{"id":104676,"name":"Sawkta","state_id":911,"state_code":"N"},{"id":104678,"name":"Seidu","state_id":911,"state_code":"N"},{"id":104683,"name":"Tintafor","state_id":911,"state_code":"N"},{"id":104687,"name":"Tonkolili","state_id":911,"state_code":"N"},{"id":104691,"name":"Yonibana","state_id":911,"state_code":"N"},{"id":104604,"name":"Baiima","state_id":912,"state_code":"S"},{"id":104605,"name":"Baoma","state_id":912,"state_code":"S"},{"id":104610,"name":"Bo","state_id":912,"state_code":"S"},{"id":104611,"name":"Bo District","state_id":912,"state_code":"S"},{"id":104614,"name":"Bomi","state_id":912,"state_code":"S"},{"id":104615,"name":"Bonthe","state_id":912,"state_code":"S"},{"id":104616,"name":"Bonthe District","state_id":912,"state_code":"S"},{"id":104619,"name":"Bumpe","state_id":912,"state_code":"S"},{"id":104622,"name":"Foindu","state_id":912,"state_code":"S"},{"id":104624,"name":"Gandorhun","state_id":912,"state_code":"S"},{"id":104626,"name":"Gbewebu","state_id":912,"state_code":"S"},{"id":104646,"name":"Koribundu","state_id":912,"state_code":"S"},{"id":104649,"name":"Largo","state_id":912,"state_code":"S"},{"id":104656,"name":"Mamboma","state_id":912,"state_code":"S"},{"id":104663,"name":"Mogbwemo","state_id":912,"state_code":"S"},{"id":104665,"name":"Moyamba","state_id":912,"state_code":"S"},{"id":104666,"name":"Moyamba District","state_id":912,"state_code":"S"},{"id":104667,"name":"Palima","state_id":912,"state_code":"S"},{"id":104671,"name":"Potoru","state_id":912,"state_code":"S"},{"id":104672,"name":"Pujehun","state_id":912,"state_code":"S"},{"id":104673,"name":"Pujehun District","state_id":912,"state_code":"S"},{"id":104675,"name":"Rotifunk","state_id":912,"state_code":"S"},{"id":104679,"name":"Serabu","state_id":912,"state_code":"S"},{"id":104681,"name":"Sumbuya","state_id":912,"state_code":"S"},{"id":104686,"name":"Tongole","state_id":912,"state_code":"S"},{"id":104692,"name":"Zimmi","state_id":912,"state_code":"S"},{"id":104623,"name":"Freetown","state_id":913,"state_code":"W"},{"id":104630,"name":"Hastings","state_id":913,"state_code":"W"},{"id":104641,"name":"Kent","state_id":913,"state_code":"W"},{"id":104688,"name":"Waterloo","state_id":913,"state_code":"W"}]